CHANGELOG.rst
CONTRIBUTING.md
LICENSE
README.rst
pyproject.toml
dmcview/__init__.py
dmcview/__main__.py
dmcview/cli.py
dmcview/compass.py
dmcview/lab/README.txt
dmcview/lab/images/lab1.png
dmcview/lab/lab1.py
dmcview/lab/lab2.py
dmcview/lab/lab3.py
dmcview/lab/lab4.py
dmcview/lab/lab5.py
dmcview/lab/lab6.py
dmcview/lab/lab7.py
dmcview/py.typed
dmcview/simulator.py
dmcview-0.1.0.dist-info/AUTHORS.md
dmcview-0.1.0.dist-info/LICENSE
dmcview-0.1.0.dist-info/METADATA
dmcview-0.1.0.dist-info/WHEEL
dmcview-0.1.0.dist-info/entry_points.txt
dmcview-0.1.0.dist-info/RECORD
