Metadata-Version: 2.1
Name: dmcview
Version: 0.1.0
Summary: Digital Magnatic Compass View
Home-page: https://github.com/Issamricin/dmc-view
License: AGPL-3.0-only
Keywords: digital Magnatic view,dmc
Author: Iso
Maintainer: Iso
Requires-Python: >=3.10,<3.13
Classifier: Development Status :: 5 - Production/Stable
Classifier: Intended Audience :: End Users/Desktop
Classifier: Intended Audience :: Manufacturing
Classifier: License :: OSI Approved :: GNU Affero General Public License v3
Classifier: Natural Language :: English
Classifier: Operating System :: MacOS
Classifier: Operating System :: POSIX :: Linux
Classifier: Operating System :: Unix
Classifier: Programming Language :: Python :: 3
Classifier: Programming Language :: Python :: 3.10
Classifier: Programming Language :: Python :: 3.11
Classifier: Programming Language :: Python :: 3.12
Classifier: Programming Language :: Python :: 3 :: Only
Classifier: Programming Language :: Python :: 3.13
Classifier: Programming Language :: Python :: 3.8
Classifier: Programming Language :: Python :: 3.9
Classifier: Topic :: Desktop Environment
Requires-Dist: mypy (>=1.8.0,<2.0.0)
Requires-Dist: pyside6 (>=6.6.1)
Requires-Dist: pytest (>=8.0.0,<9.0.0)
Requires-Dist: pytest-cov (>=4.1.0,<5.0.0)
Requires-Dist: pytest-explicit (>=1.0.1,<2.0.0)
Requires-Dist: pytest-xdist (>=3.5.0,<4.0.0)
Requires-Dist: sphinx (>=8.1.3)
Requires-Dist: sphinx-autobuild (>=2024.10.3,<2025.0.0)
Requires-Dist: sphinx-autodoc-typehints (>=2.5.0)
Requires-Dist: sphinx-inline-tabs (>=2023.4.21,<2024.0.0) ; python_version >= "3.8" and python_version < "3.13"
Requires-Dist: sphinx-rtd-theme (>=3.0.1)
Requires-Dist: sphinxcontrib-mermaid (>=1.0.0,<2.0.0) ; python_version >= "3.7" and python_version < "3.13"
Requires-Dist: sphinxcontrib-spelling (>=8.0.0)
Project-URL: Bug Tracker, https://github.com/Issamricin/dmc-view/issues
Project-URL: CI: Github Actions, https://github.com/Issamricin/dmc-view/actions
Project-URL: Changelog, https://github.com/Issamricin/dmc-view/blob/master/CHANGELOG.rst
Project-URL: Code of Conduct, https://github.com/Issamricin/dmc-view/blob/master/CONTRIBUTING.md
Project-URL: Documentation, https://dmc-view.readthedocs.io/
Project-URL: Repository, https://github.com/Issamricin/dmc-view
Project-URL: Source Code, https://github.com/Issamricin/dmc-view
